modgen/__init__.py
modgen/modgen.py
modgen-0.3.dist-info/LICENSE
modgen-0.3.dist-info/METADATA
modgen-0.3.dist-info/WHEEL
modgen-0.3.dist-info/top_level.txt
modgen-0.3.dist-info/RECORD
